spoken/__init__.py
spoken/base.py
spoken/models/gemini.py
spoken/models/nova.py
spoken/models/openai.py
spoken-0.1.1.dist-info/METADATA
spoken-0.1.1.dist-info/WHEEL
spoken-0.1.1.dist-info/licenses/LICENSE
spoken-0.1.1.dist-info/RECORD
