Metadata-Version: 2.4
Name: spoken
Version: 0.1.1
Summary: a single interface around speech-to-speech foundation models
Project-URL: repository, https://github.com/haizelabs/spoken
Project-URL: issues, https://github.com/haizelabs/spoken/issues
Author-email: Nimit Kalra <nimit@haizelabs.com>
License: MIT License
License-File: LICENSE
Classifier: Intended Audience :: Science/Research
Classifier: License :: OSI Approved :: MIT License
Classifier: Operating System :: OS Independent
Classifier: Programming Language :: Python :: 3
Requires-Python: >=3.12
Requires-Dist: instructor
Requires-Dist: loguru
Requires-Dist: numpy
Requires-Dist: openai
Requires-Dist: pydub
Requires-Dist: websockets
Provides-Extra: dev
Requires-Dist: isort; extra == 'dev'
Requires-Dist: mypy; extra == 'dev'
Requires-Dist: ruff; extra == 'dev'
Provides-Extra: nova
Requires-Dist: aws-sdk-bedrock-runtime; extra == 'nova'
Requires-Dist: pyaudio>=0.2.13; extra == 'nova'
Requires-Dist: rx>=3.2.0; extra == 'nova'
Requires-Dist: smithy-aws-core>=0.0.1; extra == 'nova'
